py_simple_launcher/__init__.py
py_simple_launcher/__main__.py
py_simple_launcher/launcher_app.py
py_simple_launcher-0.0.1.dist-info/LICENSE
py_simple_launcher-0.0.1.dist-info/METADATA
py_simple_launcher-0.0.1.dist-info/WHEEL
py_simple_launcher-0.0.1.dist-info/top_level.txt
py_simple_launcher-0.0.1.dist-info/RECORD
